fugle_realtime/__init__.py
fugle_realtime/intraday.py
tests/__init__.py
tests/test_fugle_realtime_py.py
tests/test_intraday.py
fugle_realtime_compatible-0.0.0.dist-info/LICENSE
fugle_realtime_compatible-0.0.0.dist-info/METADATA
fugle_realtime_compatible-0.0.0.dist-info/WHEEL
fugle_realtime_compatible-0.0.0.dist-info/top_level.txt
fugle_realtime_compatible-0.0.0.dist-info/RECORD
